Users/zeller/Library/Python/3.6/site-packages/fuzzingbook/01_Intro.py
Users/zeller/Library/Python/3.6/site-packages/fuzzingbook/02_Lexical_Fuzzing.py
Users/zeller/Library/Python/3.6/site-packages/fuzzingbook/03_Syntactical_Fuzzing.py
Users/zeller/Library/Python/3.6/site-packages/fuzzingbook/04_Semantical_Fuzzing.py
Users/zeller/Library/Python/3.6/site-packages/fuzzingbook/05_Domain-Specific_Fuzzing.py
Users/zeller/Library/Python/3.6/site-packages/fuzzingbook/06_Managing_Fuzzing.py
Users/zeller/Library/Python/3.6/site-packages/fuzzingbook/99_Appendices.py
Users/zeller/Library/Python/3.6/site-packages/fuzzingbook/APIFuzzer.py
Users/zeller/Library/Python/3.6/site-packages/fuzzingbook/Carver.py
Users/zeller/Library/Python/3.6/site-packages/fuzzingbook/ConcolicFuzzer.py
Users/zeller/Library/Python/3.6/site-packages/fuzzingbook/ConfigurationFuzzer.py
Users/zeller/Library/Python/3.6/site-packages/fuzzingbook/ControlFlow.py
Users/zeller/Library/Python/3.6/site-packages/fuzzingbook/Coverage.py
Users/zeller/Library/Python/3.6/site-packages/fuzzingbook/DynamicInvariants.py
Users/zeller/Library/Python/3.6/site-packages/fuzzingbook/ExpectError.py
Users/zeller/Library/Python/3.6/site-packages/fuzzingbook/Fuzzer.py
Users/zeller/Library/Python/3.6/site-packages/fuzzingbook/FuzzingInTheLarge.py
Users/zeller/Library/Python/3.6/site-packages/fuzzingbook/GUIFuzzer.py
Users/zeller/Library/Python/3.6/site-packages/fuzzingbook/GeneratorGrammarFuzzer.py
Users/zeller/Library/Python/3.6/site-packages/fuzzingbook/GrammarCoverageFuzzer.py
Users/zeller/Library/Python/3.6/site-packages/fuzzingbook/GrammarFuzzer.py
Users/zeller/Library/Python/3.6/site-packages/fuzzingbook/GrammarMiner.py
Users/zeller/Library/Python/3.6/site-packages/fuzzingbook/Grammars.py
Users/zeller/Library/Python/3.6/site-packages/fuzzingbook/GreyboxFuzzer.py
Users/zeller/Library/Python/3.6/site-packages/fuzzingbook/GreyboxGrammarFuzzer.py
fuzzingbook-0.0.5.dist-info/METADATA
fuzzingbook-0.0.5.dist-info/RECORD
fuzzingbook-0.0.5.dist-info/WHEEL
fuzzingbook-0.0.5.dist-info/top_level.txt
