Metadata-Version: 2.1
Name: fuzzingbook
Version: 0.0.5
Summary: Code for 'Generating Software Tests' (https://www.fuzzingbook.org/)
Home-page: https://www.fuzzingbook.org/
Author: Andreas Zeller et al.
Author-email: zeller@cispa.saarland
License: UNKNOWN
Platform: UNKNOWN
Classifier: Development Status :: 3 - Alpha
Classifier: Framework :: Jupyter
Classifier: Intended Audience :: Developers
Classifier: Intended Audience :: Education
Classifier: Programming Language :: Python :: 3
Classifier: License :: OSI Approved :: MIT License
Classifier: Operating System :: OS Independent
Classifier: Topic :: Software Development :: Testing
Classifier: Topic :: Education :: Testing
Classifier: Topic :: Software Development :: Quality Assurance
Classifier: Topic :: Security
